exalead_exporter/__init__.py
exalead_exporter/build_conf.py
exalead_exporter/collector.py
exalead_exporter/constants.py
exalead_exporter/core_exporter.py
exalead_exporter/exalead_api.py
exalead_exporter/exalead_exporter.py
exalead_exporter/filters.py
exalead_exporter/yamlscript.py
exalead_exporter/conf/config.yml
exalead_exporter/conf/metrics/connectorStatus.yml
exalead_exporter/conf/metrics/deploymentsStatus.yml
exalead_exporter/conf/metrics/licence_status.yml
exalead_exporter/custom_filters/__init__.py
exalead_exporter/custom_filters/defaults.py
exalead_exporter/custom_filters/hashsum.py
exalead_exporter/custom_filters/process_status.py
exalead_exporter/custom_filters/to_timestamp.py
exalead_exporter-0.0.4.dist-info/METADATA
exalead_exporter-0.0.4.dist-info/WHEEL
exalead_exporter-0.0.4.dist-info/entry_points.txt
exalead_exporter-0.0.4.dist-info/top_level.txt
exalead_exporter-0.0.4.dist-info/RECORD
