Metadata-Version: 2.1
Name: exalead-exporter
Version: 0.0.4
Summary: A Python-based Exalead for Prometheus
Home-page: https://github.com/peekjef72/exalead_exporter
Author: peekjef72
Author-email: jfpik78@gmail.com
Requires-Dist: xmltodict (==0.12.0)
Requires-Dist: tenacity (==6.2.0)
Requires-Dist: requests (>=2.20.0)
Requires-Dist: Jinja2 (==3.0.3)
Requires-Dist: urllib3 (==1.24.2)
Requires-Dist: prometheus-client (==0.14.1)
Requires-Dist: PyYAML (>=5.3.1)
Requires-Dist: python-dateutil (>=2.7.0)
